generalized_range.py
generalized_range-0.1.0a0.dist-info/licenses/LICENSE
generalized_range-0.1.0a0.dist-info/METADATA
generalized_range-0.1.0a0.dist-info/WHEEL
generalized_range-0.1.0a0.dist-info/top_level.txt
generalized_range-0.1.0a0.dist-info/RECORD
