Metadata-Version: 2.4
Name: generalized-range
Version: 0.1.0a0
Summary: A flexible Python generator function that extends the capabilities of Python's built-in `range` to all types, using customizable comparator and successor functions.
Author-email: Jifeng Wu <jifengwu2k@gmail.com>
License-Expression: MIT
Project-URL: Homepage, https://github.com/jifengwu2k/generalized-range
Project-URL: Bug Tracker, https://github.com/jifengwu2k/generalized-range/issues
Classifier: Programming Language :: Python :: 2
Classifier: Programming Language :: Python :: 3
Classifier: Operating System :: OS Independent
Requires-Python: >=2
License-File: LICENSE
Requires-Dist: typing; python_version < "3.5"
Dynamic: license-file
